streamlit_wordcloud/__init__.py
streamlit_wordcloud/streamlit_wordcloud.py
streamlit_wordcloud/utils.py
streamlit_wordcloud/frontend/build/asset-manifest.json
streamlit_wordcloud/frontend/build/bootstrap.min.css
streamlit_wordcloud/frontend/build/index.html
streamlit_wordcloud/frontend/build/precache-manifest.96c055a75f52387df534162ed71a3c37.js
streamlit_wordcloud/frontend/build/precache-manifest.9d72ee21a0c5f576da51a76e2da2ff08.js
streamlit_wordcloud/frontend/build/precache-manifest.bf2832885110282519172067500c8a64.js
streamlit_wordcloud/frontend/build/precache-manifest.ef1bf4962af1cd28593ff85f4ab184b5.js
streamlit_wordcloud/frontend/build/service-worker.js
streamlit_wordcloud/frontend/build/static/css/2.2a9431d7.chunk.css
streamlit_wordcloud/frontend/build/static/css/2.2a9431d7.chunk.css.map
streamlit_wordcloud/frontend/build/static/css/2.98f1a7d1.chunk.css
streamlit_wordcloud/frontend/build/static/css/2.98f1a7d1.chunk.css.map
streamlit_wordcloud/frontend/build/static/js/2.1b79fe21.chunk.js
streamlit_wordcloud/frontend/build/static/js/2.1b79fe21.chunk.js.LICENSE.txt
streamlit_wordcloud/frontend/build/static/js/2.1b79fe21.chunk.js.map
streamlit_wordcloud/frontend/build/static/js/2.eaec345a.chunk.js
streamlit_wordcloud/frontend/build/static/js/2.eaec345a.chunk.js.LICENSE.txt
streamlit_wordcloud/frontend/build/static/js/2.eaec345a.chunk.js.map
streamlit_wordcloud/frontend/build/static/js/main.3cca63b4.chunk.js
streamlit_wordcloud/frontend/build/static/js/main.3cca63b4.chunk.js.map
streamlit_wordcloud/frontend/build/static/js/main.65cc29d6.chunk.js
streamlit_wordcloud/frontend/build/static/js/main.65cc29d6.chunk.js.map
streamlit_wordcloud/frontend/build/static/js/main.ac4170cc.chunk.js
streamlit_wordcloud/frontend/build/static/js/main.ac4170cc.chunk.js.map
streamlit_wordcloud/frontend/build/static/js/main.cb0b4d91.chunk.js
streamlit_wordcloud/frontend/build/static/js/main.cb0b4d91.chunk.js.map
streamlit_wordcloud/frontend/build/static/js/runtime-main.11ec9aca.js
streamlit_wordcloud_v2-0.4.0.dist-info/LICENSE
streamlit_wordcloud_v2-0.4.0.dist-info/METADATA
streamlit_wordcloud_v2-0.4.0.dist-info/WHEEL
streamlit_wordcloud_v2-0.4.0.dist-info/top_level.txt
streamlit_wordcloud_v2-0.4.0.dist-info/RECORD
