Metadata-Version: 2.1
Name: streamlit-wordcloud-v2
Version: 0.4.0
Summary: Updated Wordcloud componnent based on streamlit-wordcloud by Reza Hosseini (https://github.com/rezaho/streamlit-wordcloud)
Requires-Python: >=3.6
License-File: LICENSE
Requires-Dist: streamlit (>=0.63)
Requires-Dist: numpy (>=1.20.0)
Requires-Dist: matplotlib (>=3.3.4)
